[
  {
    "file": "sample.md",
    "title": "sample",
    "date": "2025-10-29",
    "tags": [],
    "category": "",
    "description": "",
    "excerpt": "---\r title: 'CSS 스타일링 가이드'\r date: 2025-01-25\r tags: \r category: 'Tutorial'\r description: 'CSS를 사용한 모던한 웹 디자인 기법을 소개합니다.'\r ---\r \r \r \r 이 게시글에서는 모던한 CSS 기법을 사용하여 아름다운 웹사이트를 만드는 방법을 알아보겠습니다.\r \r \r \r CSS 변수..."
  },
  {
    "file": "example.md",
    "title": "example",
    "date": "2025-10-29",
    "tags": [],
    "category": "",
    "description": "",
    "excerpt": "---\r title: '첫 번째 게시글'\r date: 2025-01-26\r tags: \r category: 'Development'\r description: 'GitHub Pages 정적 블로그의 첫 번째 게시글입니다.'\r ---\r \r \r \r 안녕하세요! 이것은 GitHub Pages를 사용한 정적 블로그의 첫 번째 게시글입니다.\r \r \r \r 이 블로그는"
  }
]